jinja_compose_wrapper/__init__.py
jinja_compose_wrapper/jinja_compose.py
jinja_compose_wrapper/libjinja_compose.py
jinja_compose_wrapper/setup.py
jinja_compose_wrapper/helpers/__init__.py
jinja_compose_wrapper/helpers/const.py
jinja_compose_wrapper/helpers/io.py
jinja_compose_wrapper-0.0.4.dist-info/LICENSE
jinja_compose_wrapper-0.0.4.dist-info/METADATA
jinja_compose_wrapper-0.0.4.dist-info/WHEEL
jinja_compose_wrapper-0.0.4.dist-info/entry_points.txt
jinja_compose_wrapper-0.0.4.dist-info/top_level.txt
jinja_compose_wrapper-0.0.4.dist-info/RECORD
