Metadata-Version: 2.1
Name: jinja-compose-wrapper
Version: 0.0.4
Summary: Docker compose to the next level with Jinja2 templating
Home-page: https://github.com/Sid220/jinja-compose
Author: Sidney Trzepacz
Author-email: <lafakeslimshady@gmail.com>
License: MIT
Keywords: python,docker,compose,jinja2,template,templating
Classifier: Development Status :: 5 - Production/Stable
Classifier: Intended Audience :: Developers
Classifier: Programming Language :: Python :: 3
Classifier: Operating System :: OS Independent
Classifier: Programming Language :: Python :: Implementation :: CPython
Classifier: License :: OSI Approved :: MIT License
License-File: LICENSE
Requires-Dist: jinja2
